alogging/__init__.py
alogging/echo.py
alogging/logger.py
alogging/pp.py
alogging/filters/__init__.py
alogging/filters/default_fields.py
alogging/filters/django_sql_celery.py
alogging/filters/django_sql_excludes.py
alogging/filters/django_sql_slow_queries.py
alogging/filters/exclude.py
alogging/filters/pprint.py
alogging/filters/process_context.py
alogging/formatters/__init__.py
alogging/formatters/django_sql.py
alogging/formatters/django_sql_color.py
alogging/formatters/pprint.py
alogging/record_factories/__init__.py
alogging/record_factories/apply_filters.py
alogging-0.6.2.dist-info/AUTHORS.rst
alogging-0.6.2.dist-info/LICENSE
alogging-0.6.2.dist-info/METADATA
alogging-0.6.2.dist-info/WHEEL
alogging-0.6.2.dist-info/top_level.txt
alogging-0.6.2.dist-info/RECORD
