Metadata-Version: 2.1
Name: alogging
Version: 0.6.2
Summary: A collection of logging utilities
Home-page: https://github.com/alikins/alogging
Author: Adrian Likins
Author-email: adrian@likins.com
License: MIT license
Keywords: alogging
Platform: UNKNOWN
Classifier: Development Status :: 2 - Pre-Alpha
Classifier: Intended Audience :: Developers
Classifier: Intended Audience :: Information Technology
Classifier: Intended Audience :: System Administrators
Classifier: License :: OSI Approved :: MIT License
Classifier: Natural Language :: English
Classifier: Programming Language :: Python :: 2
Classifier: Programming Language :: Python :: 2.6
Classifier: Programming Language :: Python :: 2.7
Classifier: Programming Language :: Python :: 3
Classifier: Programming Language :: Python :: 3.6
Classifier: Programming Language :: Python :: 3.7
Classifier: Programming Language :: Python :: 3.8
Classifier: Programming Language :: Python :: 3.9
Classifier: Topic :: System :: Logging
Requires-Dist: pygments
Requires-Dist: sqlparse
Requires-Dist: logging-tree
